psql2py_core.py
psql2py_core-0.1.0.dist-info/METADATA
psql2py_core-0.1.0.dist-info/WHEEL
psql2py_core-0.1.0.dist-info/RECORD
