Metadata-Version: 2.1
Name: psql2py-core
Version: 0.1.0
Summary: 
Author: Momo Eissenhauer
Author-email: momo.eissenhauer@gmail.com
Requires-Python: >=3.11,<4.0
Classifier: Programming Language :: Python :: 3
Classifier: Programming Language :: Python :: 3.11
Requires-Dist: psycopg2 (>=2.9.5,<3.0.0)
Requires-Dist: types-psycopg2 (>=2.9.21.9,<3.0.0.0)
